{
    "AWSTemplateFormatVersion": "2010-09-09",
    "Resources": {
	"subdomains": {
	    "Type": "AWS::Route53::RecordSetGroup",
	    "Properties": {
		"HostedZoneName": "bencwik.com.",  
		"Comment": "bencwik.com production server.",
		"RecordSets": [
		    {
			"Name": "bencwik.com.",
			"Type": "A",
			"TTL": "60",
			"ResourceRecords": [
			    "52.0.217.133"
			]
		    },
		    {
			"Name": "www.bencwik.com.",
			"Type": "CNAME",
			"TTL": "60",
			"ResourceRecords": [
			    "bencwik.com"
			]
		    },
		    {
			"Name": "questionnaire.bencwik.com.",
			"Type": "CNAME",
			"TTL": "60",
			"ResourceRecords": [
			    "bencwik.com"
			]
		    },
		    {
			"Name": "www.questionnaire.bencwik.com.",
			"Type": "CNAME",
			"TTL": "60",
			"ResourceRecords": [
			    "bencwik.com"
			]
		    },
		    {
			"Name": "alientrolls.bencwik.com.",
			"Type": "CNAME",
			"TTL": "60",
			"ResourceRecords": [
			    "bencwik.com"
			]
		    },
		    {
			"Name": "www.alientrolls.bencwik.com.",
			"Type": "CNAME",
			"TTL": "60",
			"ResourceRecords": [
			    "bencwik.com"
			]
		    },
		    {
			"Name": "railscloudform.bencwik.com.",
			"Type": "CNAME",
			"TTL": "60",
			"ResourceRecords": [
			    "bencwik.com"
			]
		    },
		    {
			"Name": "www.railscloudform.bencwik.com.",
			"Type": "CNAME",
			"TTL": "60",
			"ResourceRecords": [
			    "bencwik.com"
			]
		    },
		    {
			"Name": "athleteinfo.bencwik.com.",
			"Type": "CNAME",
			"TTL": "60",
			"ResourceRecords": [
			    "bencwik.com"
			]
		    },
		    {
			"Name": "www.athleteinfo.bencwik.com.",
			"Type": "CNAME",
			"TTL": "60",
			"ResourceRecords": [
			    "bencwik.com"
			]
		    }
		]
	    }
	}
    }
}
